{
    "14互换": {
        "intro": [
            {
                "text": "注：考虑八维前需要优先考虑认知水平的对等",
                "style": {
                    "color": "#999999",
                }
            },
            {
                "text": "<span style='color: #65D0A9;'>1位和4位互换。</span>4功能是劣势功能（阿尼玛/阿尼姆斯），1功能则是英雄功能。",
                "style": {
                    "marginBottom": "32px"
                }
            },
            {
                "text": "两者相遇时，会发现自己不擅长但又渴望的点，对方可以轻而易举地做到，容易产生浪漫化吸引。",
            }
        ]
    }
}